antipathy/CHANGES
antipathy/LICENSE
antipathy/README
antipathy/__init__.py
antipathy/path.py
antipathy/test.py
antipathy-0.85.4.dist-info/METADATA
antipathy-0.85.4.dist-info/WHEEL
antipathy-0.85.4.dist-info/top_level.txt
antipathy-0.85.4.dist-info/RECORD
